adi_study_watch/__init__.py
adi_study_watch/sdk.py
adi_study_watch/application/__init__.py
adi_study_watch/application/ad7156_application.py
adi_study_watch/application/adp5360_application.py
adi_study_watch/application/adpd_application.py
adi_study_watch/application/adxl_application.py
adi_study_watch/application/bia_application.py
adi_study_watch/application/common_application.py
adi_study_watch/application/common_stream.py
adi_study_watch/application/csv_logging.py
adi_study_watch/application/ecg_application.py
adi_study_watch/application/eda_application.py
adi_study_watch/application/fs_application.py
adi_study_watch/application/low_touch_application.py
adi_study_watch/application/lt_mode4_application.py
adi_study_watch/application/pedometer_application.py
adi_study_watch/application/pm_application.py
adi_study_watch/application/ppg_application.py
adi_study_watch/application/session_manager_application.py
adi_study_watch/application/sqi_application.py
adi_study_watch/application/temperature_application.py
adi_study_watch/application/test_application.py
adi_study_watch/application/user0_application.py
adi_study_watch/application/study_watch/__init__.py
adi_study_watch/application/vsm_mb_sb/__init__.py
adi_study_watch/application/vsm_mb_sb/pm_application.py
adi_study_watch/connection/__init__.py
adi_study_watch/connection/ble_connection.py
adi_study_watch/connection/connection_interface.py
adi_study_watch/connection/ipc_tools.py
adi_study_watch/connection/serial_connection.py
adi_study_watch/core/__init__.py
adi_study_watch/core/ble_manager.py
adi_study_watch/core/packet_manager.py
adi_study_watch/core/utils.py
adi_study_watch/core/data_types/__init__.py
adi_study_watch/core/data_types/array.py
adi_study_watch/core/data_types/binary.py
adi_study_watch/core/data_types/data_type.py
adi_study_watch/core/data_types/decimal.py
adi_study_watch/core/data_types/enums.py
adi_study_watch/core/data_types/integer.py
adi_study_watch/core/data_types/string.py
adi_study_watch-5.22.1.dist-info/LICENSE
adi_study_watch-5.22.1.dist-info/METADATA
adi_study_watch-5.22.1.dist-info/WHEEL
adi_study_watch-5.22.1.dist-info/top_level.txt
adi_study_watch-5.22.1.dist-info/RECORD
