Metadata-Version: 2.1
Name: adi_study_watch
Version: 5.22.1
Summary: ADI study watch python SDK
Home-page: https://github.com/analogdevicesinc/study-watch-sdk
Author: Analog Devices, Inc.
Author-email: healthcare-support@analog.com
License: Apache License, Version 2.0
Classifier: License :: OSI Approved :: Apache Software License
Classifier: Operating System :: OS Independent
Classifier: Programming Language :: Python :: 3.6
Classifier: Programming Language :: Python :: 3.7
Classifier: Programming Language :: Python :: 3.8
Classifier: Programming Language :: Python :: 3.9
Classifier: Programming Language :: Python :: 3.10
Classifier: Intended Audience :: Healthcare Industry
Classifier: Topic :: Software Development :: Libraries
Requires-Python: >=3.6
License-File: LICENSE
Requires-Dist: pyserial ==3.5
Requires-Dist: tqdm ==4.61.0
Requires-Dist: libusb1 ==3.0.0
Requires-Dist: bleak ==0.20.2
